paypal_casinos/__init__.py
paypal_casinos-0.1.2.dist-info/WHEEL
paypal_casinos-0.1.2.dist-info/METADATA
paypal_casinos-0.1.2.dist-info/RECORD
