Metadata-Version: 2.1
Name: paypal-casinos
Version: 0.1.2
Summary: PayPal Casinos — List of Online Casinos That Accept PayPal
Home-page: https://casinos-paypal.net
Author: PayPal Casinos
Author-email: info@casinos-paypal.net
Requires-Python: >=3.7,<4.0
Classifier: Programming Language :: Python :: 3
Classifier: Programming Language :: Python :: 3.7
Classifier: Programming Language :: Python :: 3.8
Classifier: Programming Language :: Python :: 3.9
